twokenize/__init__.py
twokenize/twokenize.py
twokenize-1.0.0.dist-info/METADATA
twokenize-1.0.0.dist-info/RECORD
twokenize-1.0.0.dist-info/WHEEL
twokenize-1.0.0.dist-info/top_level.txt
