Metadata-Version: 2.1
Name: twokenize
Version: 1.0.0
Summary: Word segmentation / tokenization focussed on Twitter
Home-page: https://github.com/Sentimentron/ark-twokenize-py
Author: Richard Townsend
Author-email: richard@sentimentron.co.uk
License: GPLv3
Keywords: tokenizer
Platform: UNKNOWN
Classifier: Programming Language :: Python
Classifier: Programming Language :: Python :: 3
Classifier: Development Status :: 5 - Production/Stable
Classifier: Intended Audience :: Developers
Classifier: License :: OSI Approved :: GNU General Public License v3 (GPLv3)
Classifier: Environment :: Console
